ataskman-0.16.0.dist-info/licenses/LICENSE.txt
taskman/__init__.py
taskman/config.py
taskman/cli/__init__.py
taskman/cli/interaction.py
taskman/cli/task_manager.py
taskman/client/__init__.py
taskman/client/api_client.py
taskman/client/project_adapter.py
taskman/server/__init__.py
taskman/server/asset_manifest.py
taskman/server/project_api.py
taskman/server/route_handlers.py
taskman/server/task.py
taskman/server/task_api.py
taskman/server/task_store.py
taskman/server/tasker_server.py
taskman/server/todo/__init__.py
taskman/server/todo/todo.py
taskman/server/todo/todo_api.py
taskman/server/todo/todo_store.py
taskman/ui/filter.js
taskman/ui/index.html
taskman/ui/index.js
taskman/ui/index_api.js
taskman/ui/index_highlights.js
taskman/ui/index_people.js
taskman/ui/index_projects.js
taskman/ui/index_tags.js
taskman/ui/index_utils.js
taskman/ui/project.html
taskman/ui/project.js
taskman/ui/tasks.js
taskman/ui/todo.html
taskman/ui/todo.js
taskman/ui/styles/base.css
taskman/ui/styles/components.css
taskman/ui/styles/layout.css
taskman/ui/styles/project.css
taskman/ui/styles/tables.css
taskman/ui/styles/todo.css
ataskman-0.16.0.dist-info/METADATA
ataskman-0.16.0.dist-info/WHEEL
ataskman-0.16.0.dist-info/entry_points.txt
ataskman-0.16.0.dist-info/top_level.txt
ataskman-0.16.0.dist-info/RECORD
