Metadata-Version: 2.4
Name: ataskman
Version: 0.16.0
Summary: Simple project and task manager with CLI and UI.
Author: Ashish Gupta
License:             DO WHAT THE FUCK YOU WANT TO PUBLIC LICENSE
Requires-Python: >=3.8
License-File: LICENSE.txt
Requires-Dist: prettytable>=3.0
Provides-Extra: test
Requires-Dist: pytest; extra == "test"
Requires-Dist: pytest-cov; extra == "test"
Dynamic: license-file
